git2net/__init__.py
git2net/command_line.py
git2net/complexity.py
git2net/disambiguation.py
git2net/extraction.py
git2net/visualisation.py
git2net/helpers/binary-extensions/binary-extensions.json
tests/__init__.py
tests/test_functions.py
git2net-1.8.0.dist-info/LICENSE.txt
git2net-1.8.0.dist-info/METADATA
git2net-1.8.0.dist-info/WHEEL
git2net-1.8.0.dist-info/entry_points.txt
git2net-1.8.0.dist-info/top_level.txt
git2net-1.8.0.dist-info/RECORD
