Metadata-Version: 2.1
Name: git2net
Version: 1.8.0
Summary: An OpenSource Python package for the extraction of fine-grained and time-stamped co-editing networks from git repositories.
Home-page: https://gotec.github.io/git2net/
Author: Christoph Gote
Author-email: cgote@ethz.ch
License: AGPL-3.0+
Keywords: co-editing,network,repository,mining,network-analysis,git
Classifier: Programming Language :: Python :: 3
Classifier: License :: OSI Approved :: GNU Affero General Public License v3 or later (AGPLv3+)
Classifier: Operating System :: OS Independent
License-File: LICENSE.txt
Requires-Dist: pandas>=2.2.2
Requires-Dist: tqdm>=4.66.4
Requires-Dist: numpy>=2.0.0
Requires-Dist: scipy>=1.13.1
Requires-Dist: python-levenshtein>=0.25.1
Requires-Dist: pathpy2>=2.2.0
Requires-Dist: lizard>=1.17.10
Requires-Dist: pydriller>=2.6
Requires-Dist: gambit-disambig>=1.0.5
Requires-Dist: setuptools>=70.1.0
Requires-Dist: pygments>=2.18.0
Requires-Dist: networkx>=3.3
